{"name":"Progressimageview","tagline":"An iOS style progress ImageView for Android.","body":"### Android ProgressImageView\r\n\r\n[ ![Download](https://api.bintray.com/packages/ydcool/maven/ProgressImageView/images/download.svg) ](https://bintray.com/ydcool/maven/ProgressImageView/_latestVersion)\r\n[![Build Status](https://travis-ci.org/Ydcool/ProgressImageView.svg?branch=master)](https://travis-ci.org/Ydcool/ProgressImageView)\r\n\r\nAn iOS style progress ImageView.\r\n\r\n#### Demo\r\n\r\n![demo](https://raw.githubusercontent.com/Ydcool/QrModule/master/art/piv.gif)\r\n\r\nDemo apk [download](http://7xiilm.com1.z0.glb.clouddn.com/apk%2FProgressImageViewDemo.apk)\r\n\r\nor scan ![demo](https://api.qrserver.com/v1/create-qr-code/?data=http://7xiilm.com1.z0.glb.clouddn.com/apk%2FProgressImageViewDemo.apk&size=120x120)\r\n\r\n#### Install\r\n\r\ngradle :\r\n\r\n```java\r\n    dependencies {\r\n        compile 'me.ydcool.lib:progressimageview:latest.integration'\r\n    }\r\n```\r\n\r\n#### Usage\r\n\r\nin your layout xml:\r\n\r\n```xml\r\n<me.ydcool.lib.progressimageview.ProgressImageView\r\n        android:id=\"@+id/Main_piv\"\r\n        android:layout_width=\"200dp\"\r\n        android:layout_height=\"200dp\"\r\n        android:src=\"@mipmap/ic_launcher\"\r\n        app:pi_mask_color=\"#CC233333\"\r\n        app:pi_progress=\"0\"\r\n        app:pi_radius=\"60dp\"\r\n        app:pi_stroke=\"6dp\"/>\r\n```\r\n\r\nsetter and getter:\r\n\r\n```java\r\n    //setter\r\n    progressImageView.setProgress(yourProgress);\r\n    \r\n    //getter\r\n    int currentProgress = progressImageView.getProgress();\r\n```\r\n\r\n#### Attributes\r\n\r\n| attr | description |\r\n| ---- | ----------- |\r\n| `pi_mask_color` | mask color.argb will looks better. default is `Color.argb(180,0,0,0)` |\r\n| `pi_progress` | the progress ,default is 0. |\r\n| `pi_radius` | the radius of inner circle. default is 1/4 of the min side.|\r\n| `pi_stroke` | stroke for the transparent ring.default is 8dp. |\r\n\r\n#### TODO\r\n\r\n* support for pause and resume\r\n\r\n#### License\r\n\r\n[Apache License 2.0](LICENSE)","google":"","note":"Don't delete this file! It's used internally to help with page regeneration."}